{
  "collectionName": "components_settings_themes",
  "info": {
    "displayName": "Theme",
    "icon": "fill-drip",
    "description": ""
  },
  "options": {},
  "attributes": {
    "primary": {
      "displayName": "Color",
      "type": "component",
      "repeatable": false,
      "component": "settings.color",
      "required": true
    },
    "secondary": {
      "type": "component",
      "repeatable": false,
      "component": "settings.color",
      "required": true
    },
    "textPrimary": {
      "type": "component",
      "repeatable": false,
      "component": "settings.color"
    },
    "textSecondary": {
      "type": "component",
      "repeatable": false,
      "component": "settings.color"
    }
  }
}
